setup.py
mythe_micros/__init__.py
mythe_micros/mytest.py
mythe_micros/server.py
mythe_micros/utils.py
mythe_micros.egg-info/PKG-INFO
mythe_micros.egg-info/SOURCES.txt
mythe_micros.egg-info/dependency_links.txt
mythe_micros.egg-info/top_level.txt