Metadata-Version: 1.0
Name: mythe-micros
Version: 0.0.1
Summary: Easy Micro Service Library
Home-page: UNKNOWN
Author: Mythezone
Author-email: 125616515@qq.com
License: MIT Licence
Keywords: pip,micro,service
Platform: UNKNOWN
